hamrobazaar/aioclient.py
hamrobazaar/exceptions.py
hamrobazaar/types.py
hamrobazaar/utils.py
hamrobazaar-0.1.0.dist-info/WHEEL
hamrobazaar-0.1.0.dist-info/METADATA
hamrobazaar-0.1.0.dist-info/RECORD
